{"is_source_file": true, "format": "md", "description": ".md file: README.md", "external_files": [], "external_methods": [], "published": [], "classes": [], "methods": [], "calls": [], "search-terms": ["README.md", "md"], "state": 2, "file_id": 1, "knowledge_revision": 48, "git_revision": "7999122821b224f05febc219d8fc5ce03bddbcee", "revision_history": [{"33": "bb0c0db04a3af0e13d15b89f7c4b6849952a817f"}, {"48": "7999122821b224f05febc219d8fc5ce03bddbcee"}], "filename": "README.md", "format-version": 4, "code-base-name": "https://github.com/kavia-common/simple-notes-app-45066-45076.git:kavia-main"}